README.rst
setup.py
similar_text/__init__.py
similar_text/similar_text.py
similar_text.egg-info/PKG-INFO
similar_text.egg-info/SOURCES.txt
similar_text.egg-info/dependency_links.txt
similar_text.egg-info/top_level.txt