Metadata-Version: 1.1
Name: similar-text
Version: 0.2.0
Summary: Calculates the similarity between two strings
Home-page: https://github.com/luosch/similar_text
Author: Sicheng Luo
Author-email: i@lsich.com
License: MIT
Keywords: similar_text,similar,text
Platform: UNKNOWN
Classifier: License :: OSI Approved :: MIT License
Classifier: Programming Language :: Python
Classifier: Intended Audience :: Developers
Classifier: Operating System :: OS Independent
Classifier: Programming Language :: Python
Classifier: Programming Language :: Python :: 2.7
